configDmanager/__init__.py
configDmanager/_config.py
configDmanager/_configmanager.py
configDmanager/_format.py
configDmanager/config_types.py
configDmanager/errors.py
ConfigDmanager-0.2.0.dist-info/LICENSE
ConfigDmanager-0.2.0.dist-info/METADATA
ConfigDmanager-0.2.0.dist-info/WHEEL
ConfigDmanager-0.2.0.dist-info/top_level.txt
ConfigDmanager-0.2.0.dist-info/RECORD
