Metadata-Version: 2.1
Name: ConfigDmanager
Version: 0.2.0
Summary: A simple configuration files manager package
Home-page: https://github.com/hmiladhia/ConfigDmanager
Author: Dhia Hmila
Author-email: hmiladhia@hotmail.fr
License: UNKNOWN
Platform: UNKNOWN
Classifier: Programming Language :: Python :: 3
Classifier: License :: OSI Approved :: MIT License
Classifier: Operating System :: OS Independent
Requires-Python: >= 3.6
Requires-Dist: pyyaml
